Metadata-Version: 2.1
Name: maykin-django-two-factor-auth
Version: 2.0.4
Summary: Fork of "django-two-factor-auth" featuring a complete Two-Factor Authentication system for Django
Home-page: https://github.com/maykinmedia/django-two-factor-auth
Author: Bouke Haarsma
Author-email: bouke@haarsma.eu
License: MIT
Download-URL: https://pypi.python.org/pypi/maykin-django-two-factor-auth
Platform: UNKNOWN
Classifier: Development Status :: 5 - Production/Stable
Classifier: Environment :: Web Environment
Classifier: Framework :: Django
Classifier: Framework :: Django :: 2.2
Classifier: Framework :: Django :: 3.0
Classifier: Framework :: Django :: 3.1
Classifier: Intended Audience :: Developers
Classifier: License :: OSI Approved :: MIT License
Classifier: Operating System :: OS Independent
Classifier: Programming Language :: Python
Classifier: Programming Language :: Python :: 3
Classifier: Programming Language :: Python :: 3 :: Only
Classifier: Programming Language :: Python :: 3.5
Classifier: Programming Language :: Python :: 3.6
Classifier: Programming Language :: Python :: 3.7
Classifier: Programming Language :: Python :: 3.8
Classifier: Topic :: Security
Classifier: Topic :: System :: Systems Administration :: Authentication/Directory
License-File: LICENSE
Requires-Dist: Django (<4.0.0,>=2.2.0)
Requires-Dist: django-otp (>=1.0.0.<2.0.0)
Requires-Dist: qrcode (<6.99,>=4.0.0)
Requires-Dist: django-phonenumber-field (<6.0.0,>=5.0.0)
Requires-Dist: django-formtools
Provides-Extra: call
Requires-Dist: twilio (>=6.0) ; extra == 'call'
Provides-Extra: phonenumbers
Requires-Dist: phonenumbers (<8.99,>=7.0.9) ; extra == 'phonenumbers'
Provides-Extra: phonenumberslite
Requires-Dist: phonenumberslite (<8.99,>=7.0.9) ; extra == 'phonenumberslite'
Provides-Extra: sms
Requires-Dist: twilio (>=6.0) ; extra == 'sms'
Provides-Extra: yubikey
Requires-Dist: django-otp-yubikey ; extra == 'yubikey'
